{
  "users": [
    {
      "id": 1,
      "name": "Clifton",
      "email": "clif@gmail.com",
      "password": "Clifmatski1"
    },
    {
      "id": 2,
      "name": "Josh",
      "email": "hipsterbro@gmail.com",
      "password": "dicktags"
    },
    {
      "name": "Kristen",
      "email": "kristen@gmail.com",
      "password": "1234",
      "id": 3
    },
    {
      "name": "amber@gmail.com",
      "email": "1234",
      "password": "fun",
      "id": 4
    },
    {
      "name": "amber",
      "email": "amber@gmail.com",
      "password": "1234",
      "id": 5
    }
  ],
  "books": [
    {
      "title": " The Dragon Reborn ",
      "author": "Robert Jordan",
      "imgUrl": "http://books.google.com/books/content?id=4nWghD8QV0IC&printsec=frontcover&img=1&zoom=1&edge=curl&source=gbs_api",
      "userId": 3,
      "id": 3
    },
    {
      "title": " Mistborn Trilogy ",
      "author": "Brandon Sanderson",
      "imgUrl": "http://books.google.com/books/content?id=F8u01NaEZU0C&printsec=frontcover&img=1&zoom=1&edge=curl&source=gbs_api",
      "userId": 1,
      "id": 5
    },
    {
      "title": " Words of Radiance ",
      "author": "Brandon Sanderson",
      "imgUrl": "http://books.google.com/books/content?id=cZbQAgAAQBAJ&printsec=frontcover&img=1&zoom=1&edge=curl&source=gbs_api",
      "userId": 3,
      "id": 7
    },
    {
      "title": " Mistborn ",
      "author": "Brandon Sanderson",
      "imgUrl": "http://books.google.com/books/content?id=q0pF7ly_vTEC&printsec=frontcover&img=1&zoom=1&edge=curl&source=gbs_api",
      "userId": 2,
      "id": 8
    },
    {
      "title": "Robert JordanHarriet McDougalAlan RomanczukMaria Simons",
      "author": "Since its debut in 1990, The Wheel of Time速 by Robert Jordan has captivated millions of readers around the globe with its scope, originality, and compelling characters. Over the course of fifteen books and millions of words, the world that Jordan created grew in depth and complexity. However, only a fraction of what Jordan imagined ended up on the page, the rest going into his personal files. Now The Wheel of Time Companion sheds light on some of the most intriguing aspects of the world, including biographies and motivations of many characters that never made it into the books, but helped bring Jordan's world to life. Included in the volume in an A-to-Z format are: An entry for each named character An inclusive dictionary of the Old Tongue New maps of the Last Battle New portraits of many characters Histories and customs of the nations of the world The strength level of many channelers Descriptions of the flora and fauna unique to the world And much more! The Wheel of Time Companion will be required reading for The Wheel of Time's millions of fans. The Wheel of Time速 New Spring: The Novel #1 The Eye of the World #2 The Great Hunt #3 The Dragon Reborn #4 The Shadow Rising #5 The Fires of Heaven #6 Lord of Chaos #7 A Crown of Swords #8 The Path of Daggers #9 Winter's Heart #10 Crossroads of Twilight #11 Knife of Dreams By Robert Jordan and Brandon Sanderson #12 The Gathering Storm #13 Towers of Midnight #14 A Memory of Light By Robert Jordan and Teresa Patterson The World of Robert Jordan's The Wheel of Time By Robert Jordan, Harriet McDougal, Alan Romanczuk, and Maria Simons The Wheel of Time Companion By Robert Jordan and Amy Romanczuk Patterns of the Wheel: Coloring Art Based on Robert Jordan's The Wheel of Time At the Publisher's request, this title is being sold without Digital Rights Management Software (DRM) applied.",
      "summary": "Since its debut in 1990, The Wheel of Time速 by Robert Jordan has captivated millions of readers around the globe with its scope, originality, and compelling characters. Over the course of fifteen books and millions of words, the world that Jordan created grew in depth and complexity. However, only a fraction of what Jordan imagined ended up on the page, the rest going into his personal files. Now The Wheel of Time Companion sheds light on some of the most intriguing aspects of the world, including biographies and motivations of many characters that never made it into the books, but helped bring Jordan's world to life. Included in the volume in an A-to-Z format are: An entry for each named character An inclusive dictionary of the Old Tongue New maps of the Last Battle New portraits of many characters Histories and customs of the nations of the world The strength level of many channelers Descriptions of the flora and fauna unique to the world And much more! The Wheel of Time Companion will be required reading for The Wheel of Time's millions of fans. The Wheel of Time速 New Spring: The Novel #1 The Eye of the World #2 The Great Hunt #3 The Dragon Reborn #4 The Shadow Rising #5 The Fires of Heaven #6 Lord of Chaos #7 A Crown of Swords #8 The Path of Daggers #9 Winter's Heart #10 Crossroads of Twilight #11 Knife of Dreams By Robert Jordan and Brandon Sanderson #12 The Gathering Storm #13 Towers of Midnight #14 A Memory of Light By Robert Jordan and Teresa Patterson The World of Robert Jordan's The Wheel of Time By Robert Jordan, Harriet McDougal, Alan Romanczuk, and Maria Simons The Wheel of Time Companion By Robert Jordan and Amy Romanczuk Patterns of the Wheel: Coloring Art Based on Robert Jordan's The Wheel of Time At the Publisher's request, this title is being sold without Digital Rights Management Software (DRM) applied.",
      "imgUrl": "http://books.google.com/books/content?id=5P5oCAAAQBAJ&printsec=frontcover&img=1&zoom=1&edge=curl&source=gbs_api",
      "userId": 1,
      "id": 10
    },
    {
      "title": " Mistborn ",
      "author": "Brandon Sanderson",
      "summary": " Mistborn ",
      "imgUrl": "http://books.google.com/books/content?id=q0pF7ly_vTEC&printsec=frontcover&img=1&zoom=1&edge=curl&source=gbs_api",
      "userId": 1,
      "id": 11
    }
  ],
  "reviews": [],
  "friends": []
}